<?xml version="1.0" encoding="UTF-8"?>
<HtmlElements>
	<Group Name="Common controls">
		<Element Name="Canvas"></Element>
		<Element Name="Command"></Element>		
		<Element Name="DataList"></Element>
		<Element Name="Details"></Element>
		<Element Name="Figure"></Element>
		<Element Name="FigCaption"></Element>
		<Element Name="Iframe"></Element>
		<Element Name="InputButton"></Element>
		<Element Name="InputSubmit"></Element>
		<Element Name="InputReset"></Element>
		<Element Name="InputCheckBox"></Element>
		<Element Name="InputFile"></Element>
		<Element Name="InputText"></Element>
		<Element Name="InputPassword"></Element>
		<Element Name="InputRadio"></Element>
		<Element Name="InputColor"></Element>
		<Element Name="InputDate"></Element>
		<Element Name="InputDatetime"></Element>
		<Element Name="InputDatetime-local"></Element>
		<Element Name="InputEmail"></Element>
		<Element Name="InputMonth"></Element>
		<Element Name="InputNumber"></Element>
		<Element Name="InputRange"></Element>
		<Element Name="InputSearch"></Element>
		<Element Name="InputTime"></Element>
		<Element Name="InputUrl"></Element>
		<Element Name="InputWeek"></Element>
		<Element Name="InputImage"></Element>
		<Element Name="Image"></Element>
		<Element Name="Keygen"></Element>
		<Element Name="Label"></Element>
		<Element Name="MessageBox"></Element>
		<Element Name="Meter"></Element>
		<Element Name="Map"></Element>
		<Element Name="Nav"></Element>
		<Element Name="Output"></Element>
		<Element Name="Progress"></Element>
		<Element Name="Area"></Element>
		<Element Name="Address"></Element>
		<Element Name="Select"></Element>
		<Element Name="Summary"></Element>
		<!--<Element Name="Svg"></Element>-->
		<Element Name="Table"></Element>
		<Element Name="TextArea"></Element>
		<Element Name="TimeTag"></Element>
		<!--<Element Name="ScrollBar"></Element>-->
	</Group>
	<Group Name="Layout">
		<Element Name="A"></Element>
		<Element Name="Abbr"></Element>
		<Element Name="Article"></Element>
		<Element Name="Aside"></Element>
		<Element Name="Bdi"></Element>
		<Element Name="Footer"></Element>
		<Element Name="Header"></Element>
		<Element Name="Hgroup"></Element>
		<Element Name="Mark"></Element>
		<Element Name="Wbr"></Element>
		<Element Name="Blockquote"></Element>
		<Element Name="Cite"></Element>
		<Element Name="Code"></Element>
		<Element Name="Dl"></Element>
		<Element Name="Dt"></Element>
		<Element Name="Dd"></Element>
		<Element Name="Del"></Element>
		<Element Name="Dfn"></Element>
		<Element Name="Div"></Element>
		<Element Name="Em"></Element>
		<Element Name="Embed"></Element>
		<Element Name="Fieldset"></Element>
		<Element Name="Frame"></Element>
		<Element Name="H1"></Element>
		<Element Name="H2"></Element>
		<Element Name="H3"></Element>
		<Element Name="H4"></Element>
		<Element Name="H5"></Element>
		<Element Name="H6"></Element>
		<Element Name="Ins"></Element>
		<Element Name="kdb"></Element>
		<Element Name="Label"></Element>
		<Element Name="Legend"></Element>
		<Element Name="Object"></Element>
		<Element Name="Ol"></Element>
		<Element Name="Ul"></Element>
		<Element Name="Li"></Element>
		<Element Name="P"></Element>
		<Element Name="Pre"></Element>
		<Element Name="Rp"></Element>
		<Element Name="Rt"></Element>
		<Element Name="Ruby"></Element>
		<Element Name="Q"></Element>
		<Element Name="Samp"></Element>
		<Element Name="Section"></Element>
		<Element Name="Small"></Element>
		<Element Name="span"></Element>
		<Element Name="Strong"></Element>
		<Element Name="sub"></Element>
		<Element Name="sup"></Element>
		<Element Name="Td"></Element>
		<Element Name="Th"></Element>
		<Element Name="Var"></Element>
	</Group>
	<Group Name="Media">		
		<Element Name="Video"></Element>
		<Element Name="Audio"></Element>
		<Element Name="Embed"></Element>		
	</Group>	
</HtmlElements>